README.txt
setup.py
anad_dev/__init__.py
anad_dev/ecrypt.py
anad_dev/send_gmail.py
anad_dev.egg-info/PKG-INFO
anad_dev.egg-info/SOURCES.txt
anad_dev.egg-info/dependency_links.txt
anad_dev.egg-info/top_level.txt